README.md
setup.py
aanalyticsact_1/__init__.py
aanalyticsact_1/__version__.py
aanalyticsact_1/actExecute.py
aanalyticsact_1/actModuler.py
aanalyticsact_1/actRunner.py
aanalyticsact_1.egg-info/PKG-INFO
aanalyticsact_1.egg-info/SOURCES.txt
aanalyticsact_1.egg-info/dependency_links.txt
aanalyticsact_1.egg-info/not-zip-safe
aanalyticsact_1.egg-info/requires.txt
aanalyticsact_1.egg-info/top_level.txt